LICENSE.txt
MANIFEST.in
README.rst
VERSION
setup.cfg
setup.py
betfairng/__init__.py
betfairng/betfairng.py
betfairng/legacyv6.py
betfairng.egg-info/PKG-INFO
betfairng.egg-info/SOURCES.txt
betfairng.egg-info/dependency_links.txt
betfairng.egg-info/requires.txt
betfairng.egg-info/top_level.txt