Metadata-Version: 1.1
Name: betfairng
Version: 0.1.5
Summary: Client library for Betfair API Next-Generation
Home-page: http://www.tagwager.com/
Author: Russell Gray
Author-email: russgray@gmail.com
License: BSD 2-Clause
Download-URL: http://www.tagwager.com/
Keywords: betfair,aping,tagwager
Platform: UNKNOWN
Classifier: Programming Language :: Python
Classifier: Programming Language :: Python :: 2.7
Classifier: Development Status :: 4 - Beta
Classifier: Environment :: Other Environment
Classifier: Intended Audience :: Developers
Classifier: Operating System :: OS Independent
Classifier: Topic :: Software Development :: Libraries :: Python Modules
Classifier: License :: OSI Approved :: BSD License
